ricochet_tech/__init__.py
ricochet_tech/audio/__init__.py
ricochet_tech/audio/audio_util.py
ricochet_tech/audio/float32_helpers.py
at_audioutil_pkg-0.0.5.dist-info/METADATA
at_audioutil_pkg-0.0.5.dist-info/WHEEL
at_audioutil_pkg-0.0.5.dist-info/entry_points.txt
at_audioutil_pkg-0.0.5.dist-info/top_level.txt
at_audioutil_pkg-0.0.5.dist-info/RECORD
